<archimate:ArchimateDiagramModel
    xmlns:xsi="http://www.w3.org/2001/XMLSchema-instance"
    xmlns:archimate="http://www.archimatetool.com/archimate"
    name="TB_KK_SCH (2020): Technologická vrstva JPMIS"
    id="ca09c662">
  <children
      xsi:type="archimate:DiagramModelGroup"
      id="ae6cc33a"
      name="Technologická architektura"
      font="1|Segoe UI|9.0|0|WINDOWS|1|0|0|0|0|0|0|0|0|1|0|0|0|0|Segoe UI"
      fontColor="#000000"
      lineColor="#5c5c5c"
      textAlignment="1"
      fillColor="#e2f1d8">
    <bounds
        x="50"
        y="100"
        width="1800"
        height="250"/>
    <children
        xsi:type="archimate:DiagramModelArchimateObject"
        id="b80de380"
        targetConnections="c993e8ed"
        font="1|Segoe UI|9.0|0|WINDOWS|1|0|0|0|0|0|0|0|0|1|0|0|0|0|Segoe UI"
        fontColor="#000000"
        lineColor="#5c5c5c"
        fillColor="#c9e7b7">
      <bounds
          x="150"
          y="50"
          width="120"
          height="55"/>
      <archimateElement
          xsi:type="archimate:TechnologyService"
          href="TechnologyService_id-70a895a8.xml#id-70a895a8"/>
    </children>
    <children
        xsi:type="archimate:DiagramModelArchimateObject"
        id="id-5607008f"
        targetConnections="id-22429f96"
        font="1|Segoe UI|9.0|0|WINDOWS|1|0|0|0|0|0|0|0|0|1|0|0|0|0|Segoe UI"
        fontColor="#000000"
        lineColor="#5c5c5c"
        fillColor="#c9e7b7">
      <bounds
          x="550"
          y="50"
          width="151"
          height="55"/>
      <archimateElement
          xsi:type="archimate:TechnologyService"
          href="TechnologyService_d9926cda.xml#d9926cda"/>
    </children>
    <children
        xsi:type="archimate:DiagramModelArchimateObject"
        id="ad669d5b"
        targetConnections="e5758a6b"
        font="1|Segoe UI|9.0|0|WINDOWS|1|0|0|0|0|0|0|0|0|1|0|0|0|0|Segoe UI"
        fontColor="#000000"
        lineColor="#5c5c5c"
        fillColor="#c9e7b7">
      <sourceConnections
          xsi:type="archimate:DiagramModelArchimateConnection"
          id="c6d805e0"
          font="1|Segoe UI|9.0|0|WINDOWS|1|0|0|0|0|0|0|0|0|1|0|0|0|0|Segoe UI"
          fontColor="#000000"
          lineColor="#000000"
          source="ad669d5b"
          target="id-6c30b2f5">
        <archimateRelationship
            xsi:type="archimate:CompositionRelationship"
            href="CompositionRelationship_f1ccf731.xml#f1ccf731"/>
      </sourceConnections>
      <bounds
          x="950"
          y="50"
          width="301"
          height="55"/>
      <archimateElement
          xsi:type="archimate:TechnologyService"
          href="TechnologyService_id-17a7119c.xml#id-17a7119c"/>
    </children>
    <children
        xsi:type="archimate:DiagramModelArchimateObject"
        id="id-6c30b2f5"
        targetConnections="c6d805e0"
        font="1|Segoe UI|9.0|0|WINDOWS|1|0|0|0|0|0|0|0|0|1|0|0|0|0|Segoe UI"
        fontColor="#000000"
        lineColor="#5c5c5c"
        fillColor="#c9e7b7">
      <bounds
          x="950"
          y="137"
          width="120"
          height="55"/>
      <archimateElement
          xsi:type="archimate:TechnologyService"
          href="TechnologyService_id-36e3c17c.xml#id-36e3c17c"/>
    </children>
    <children
        xsi:type="archimate:DiagramModelArchimateObject"
        id="id-86a2405f"
        targetConnections="id-5fc88a63"
        font="1|Segoe UI|9.0|0|WINDOWS|1|0|0|0|0|0|0|0|0|1|0|0|0|0|Segoe UI"
        fontColor="#000000"
        lineColor="#5c5c5c"
        fillColor="#c9e7b7">
      <bounds
          x="1324"
          y="50"
          width="120"
          height="55"/>
      <archimateElement
          xsi:type="archimate:TechnologyService"
          href="TechnologyService_e7aad88f.xml#e7aad88f"/>
    </children>
    <children
        xsi:type="archimate:DiagramModelArchimateObject"
        id="id-8b7a6a3e"
        targetConnections="ae4b44b8"
        font="1|Segoe UI|9.0|0|WINDOWS|1|0|0|0|0|0|0|0|0|1|0|0|0|0|Segoe UI"
        fontColor="#000000"
        lineColor="#5c5c5c"
        fillColor="#ffeaff">
      <bounds
          x="700"
          y="50"
          width="181"
          height="55"/>
      <archimateElement
          xsi:type="archimate:TechnologyService"
          href="TechnologyService_id-5ba8fa84.xml#id-5ba8fa84"/>
    </children>
    <children
        xsi:type="archimate:DiagramModelArchimateObject"
        id="id-4459954b"
        font="1|Segoe UI|9.0|0|WINDOWS|1|0|0|0|0|0|0|0|0|1|0|0|0|0|Segoe UI"
        fontColor="#000000"
        lineColor="#5c5c5c"
        fillColor="#c9e7b7">
      <bounds
          x="1450"
          y="50"
          width="301"
          height="55"/>
      <archimateElement
          xsi:type="archimate:TechnologyService"
          href="TechnologyService_id-6d48f37e.xml#id-6d48f37e"/>
    </children>
    <children
        xsi:type="archimate:DiagramModelArchimateObject"
        id="id-2320e869-ecef-4683-b901-0bc65b358137"
        targetConnections="f3cfdf7a-7054-49eb-add2-368f6e9529c5"
        font="1|Segoe UI|9.0|0|WINDOWS|1|0|0|0|0|0|0|0|0|1|0|0|0|0|Segoe UI"
        fontColor="#000000"
        lineColor="#5c5c5c"
        fillColor="#c9e7b7">
      <bounds
          x="312"
          y="50"
          width="193"
          height="55"/>
      <archimateElement
          xsi:type="archimate:TechnologyService"
          href="TechnologyService_id-2a389c8a.xml#id-2a389c8a"/>
    </children>
  </children>
  <children
      xsi:type="archimate:DiagramModelGroup"
      id="ce1ae620"
      name="Infrastrukturní architektura"
      font="1|Segoe UI|9.0|0|WINDOWS|1|0|0|0|0|0|0|0|0|1|0|0|0|0|Segoe UI"
      fontColor="#000000"
      lineColor="#5c5c5c"
      textAlignment="1"
      fillColor="#c8ffc8">
    <bounds
        x="50"
        y="400"
        width="1800"
        height="250"/>
    <children
        xsi:type="archimate:DiagramModelArchimateObject"
        id="c6cdcde8"
        targetConnections="id-82e12892"
        font="1|Segoe UI|9.0|0|WINDOWS|1|0|0|0|0|0|0|0|0|1|0|0|0|0|Segoe UI"
        fontColor="#000000"
        lineColor="#5c5c5c"
        fillColor="#c8ffc8"
        type="1">
      <sourceConnections
          xsi:type="archimate:DiagramModelArchimateConnection"
          id="f28b544e"
          font="1|Segoe UI|9.0|0|WINDOWS|1|0|0|0|0|0|0|0|0|1|0|0|0|0|Segoe UI"
          fontColor="#000000"
          lineColor="#000000"
          source="c6cdcde8"
          target="id-4bfbffff">
        <archimateRelationship
            xsi:type="archimate:CompositionRelationship"
            href="CompositionRelationship_fd315a04.xml#fd315a04"/>
      </sourceConnections>
      <sourceConnections
          xsi:type="archimate:DiagramModelArchimateConnection"
          id="id-09de74d8"
          font="1|Segoe UI|9.0|0|WINDOWS|1|0|0|0|0|0|0|0|0|1|0|0|0|0|Segoe UI"
          fontColor="#000000"
          lineColor="#000000"
          source="c6cdcde8"
          target="id-09eab30d">
        <archimateRelationship
            xsi:type="archimate:ServingRelationship"
            href="ServingRelationship_id-42378520.xml#id-42378520"/>
      </sourceConnections>
      <sourceConnections
          xsi:type="archimate:DiagramModelArchimateConnection"
          id="cac8f437"
          font="1|Segoe UI|9.0|0|WINDOWS|1|0|0|0|0|0|0|0|0|1|0|0|0|0|Segoe UI"
          fontColor="#000000"
          lineColor="#000000"
          source="c6cdcde8"
          target="d5c17911">
        <archimateRelationship
            xsi:type="archimate:CompositionRelationship"
            href="CompositionRelationship_id-95838598.xml#id-95838598"/>
      </sourceConnections>
      <bounds
          x="400"
          y="189"
          width="682"
          height="51"/>
      <archimateElement
          xsi:type="archimate:Node"
          href="Node_a47d4535.xml#a47d4535"/>
    </children>
    <children
        xsi:type="archimate:DiagramModelArchimateObject"
        id="ac8fb402"
        font="1|Segoe UI|9.0|0|WINDOWS|1|0|0|0|0|0|0|0|0|1|0|0|0|0|Segoe UI"
        fontColor="#000000"
        lineColor="#5c5c5c"
        fillColor="#c8ffc8"
        type="1">
      <sourceConnections
          xsi:type="archimate:DiagramModelArchimateConnection"
          id="id-412cf18a"
          font="1|Segoe UI|9.0|0|WINDOWS|1|0|0|0|0|0|0|0|0|1|0|0|0|0|Segoe UI"
          fontColor="#000000"
          lineColor="#000000"
          source="ac8fb402"
          target="id-09eab30d">
        <archimateRelationship
            xsi:type="archimate:ServingRelationship"
            href="ServingRelationship_id-6c77a2f6.xml#id-6c77a2f6"/>
      </sourceConnections>
      <bounds
          x="1531"
          y="185"
          width="120"
          height="55"/>
      <archimateElement
          xsi:type="archimate:Device"
          href="Device_id-471a65b7.xml#id-471a65b7"/>
    </children>
    <children
        xsi:type="archimate:DiagramModelArchimateObject"
        id="id-03651637"
        targetConnections="id-612d7f4b"
        font="1|Segoe UI|9.0|0|WINDOWS|1|0|0|0|0|0|0|0|0|1|0|0|0|0|Segoe UI"
        fontColor="#000000"
        lineColor="#5c5c5c"
        fillColor="#c8ffc8"
        type="1">
      <bounds
          x="98"
          y="185"
          width="120"
          height="55"/>
      <archimateElement
          xsi:type="archimate:Node"
          href="Node_id-31af505a.xml#id-31af505a"/>
    </children>
    <children
        xsi:type="archimate:DiagramModelArchimateObject"
        id="id-2329c9a6"
        font="1|Segoe UI|9.0|0|WINDOWS|1|0|0|0|0|0|0|0|0|1|0|0|0|0|Segoe UI"
        fontColor="#000000"
        lineColor="#5c5c5c"
        fillColor="#c8ffc8">
      <sourceConnections
          xsi:type="archimate:DiagramModelArchimateConnection"
          id="c993e8ed"
          font="1|Segoe UI|9.0|0|WINDOWS|1|0|0|0|0|0|0|0|0|1|0|0|0|0|Segoe UI"
          fontColor="#000000"
          lineColor="#000000"
          source="id-2329c9a6"
          target="b80de380">
        <archimateRelationship
            xsi:type="archimate:ServingRelationship"
            href="ServingRelationship_ce08da29.xml#ce08da29"/>
      </sourceConnections>
      <bounds
          x="100"
          y="50"
          width="120"
          height="55"/>
      <archimateElement
          xsi:type="archimate:TechnologyInterface"
          href="TechnologyInterface_id-06e3b9f1.xml#id-06e3b9f1"/>
    </children>
    <children
        xsi:type="archimate:DiagramModelArchimateObject"
        id="id-8ee6d168"
        font="1|Segoe UI|9.0|0|WINDOWS|1|0|0|0|0|0|0|0|0|1|0|0|0|0|Segoe UI"
        fontColor="#000000"
        lineColor="#5c5c5c"
        fillColor="#c8ffc8">
      <sourceConnections
          xsi:type="archimate:DiagramModelArchimateConnection"
          id="id-82e12892"
          font="1|Segoe UI|9.0|0|WINDOWS|1|0|0|0|0|0|0|0|0|1|0|0|0|0|Segoe UI"
          fontColor="#000000"
          lineColor="#000000"
          source="id-8ee6d168"
          target="c6cdcde8">
        <archimateRelationship
            xsi:type="archimate:AssociationRelationship"
            href="AssociationRelationship_f5be999f.xml#f5be999f"/>
      </sourceConnections>
      <sourceConnections
          xsi:type="archimate:DiagramModelArchimateConnection"
          id="id-612d7f4b"
          font="1|Segoe UI|9.0|0|WINDOWS|1|0|0|0|0|0|0|0|0|1|0|0|0|0|Segoe UI"
          fontColor="#000000"
          lineColor="#000000"
          source="id-8ee6d168"
          target="id-03651637">
        <archimateRelationship
            xsi:type="archimate:AssociationRelationship"
            href="AssociationRelationship_dd9480a7.xml#dd9480a7"/>
      </sourceConnections>
      <bounds
          x="229"
          y="185"
          width="120"
          height="55"/>
      <archimateElement
          xsi:type="archimate:CommunicationNetwork"
          href="CommunicationNetwork_cc6dafb9.xml#cc6dafb9"/>
    </children>
    <children
        xsi:type="archimate:DiagramModelArchimateObject"
        id="id-8b845021"
        font="1|Segoe UI|9.0|0|WINDOWS|1|0|0|0|0|0|0|0|0|1|0|0|0|0|Segoe UI"
        fontColor="#000000"
        lineColor="#5c5c5c"
        fillColor="#c8ffc8"
        type="1">
      <sourceConnections
          xsi:type="archimate:DiagramModelArchimateConnection"
          id="e5758a6b"
          font="1|Segoe UI|9.0|0|WINDOWS|1|0|0|0|0|0|0|0|0|1|0|0|0|0|Segoe UI"
          fontColor="#000000"
          lineColor="#000000"
          source="id-8b845021"
          target="ad669d5b">
        <archimateRelationship
            xsi:type="archimate:RealizationRelationship"
            href="RealizationRelationship_id-5f9cedff.xml#id-5f9cedff"/>
      </sourceConnections>
      <sourceConnections
          xsi:type="archimate:DiagramModelArchimateConnection"
          id="id-5fc88a63"
          font="1|Segoe UI|9.0|0|WINDOWS|1|0|0|0|0|0|0|0|0|1|0|0|0|0|Segoe UI"
          fontColor="#000000"
          lineColor="#000000"
          source="id-8b845021"
          target="id-86a2405f">
        <archimateRelationship
            xsi:type="archimate:RealizationRelationship"
            href="RealizationRelationship_id-6ca62539.xml#id-6ca62539"/>
      </sourceConnections>
      <sourceConnections
          xsi:type="archimate:DiagramModelArchimateConnection"
          id="id-2312780c"
          font="1|Segoe UI|9.0|0|WINDOWS|1|0|0|0|0|0|0|0|0|1|0|0|0|0|Segoe UI"
          fontColor="#000000"
          lineColor="#000000"
          source="id-8b845021"
          target="d5c17911">
        <archimateRelationship
            xsi:type="archimate:CompositionRelationship"
            href="CompositionRelationship_id-07c81cd7.xml#id-07c81cd7"/>
      </sourceConnections>
      <sourceConnections
          xsi:type="archimate:DiagramModelArchimateConnection"
          id="ae4b44b8"
          font="1|Segoe UI|9.0|0|WINDOWS|1|0|0|0|0|0|0|0|0|1|0|0|0|0|Segoe UI"
          fontColor="#000000"
          lineColor="#000000"
          source="id-8b845021"
          target="id-8b7a6a3e">
        <archimateRelationship
            xsi:type="archimate:RealizationRelationship"
            href="RealizationRelationship_id-6233747a.xml#id-6233747a"/>
      </sourceConnections>
      <bounds
          x="750"
          y="50"
          width="901"
          height="55"/>
      <archimateElement
          xsi:type="archimate:Node"
          href="Node_id-2d01ba72.xml#id-2d01ba72"/>
    </children>
    <children
        xsi:type="archimate:DiagramModelArchimateObject"
        id="d5c17911"
        targetConnections="cac8f437 id-2312780c"
        font="1|Segoe UI|9.0|0|WINDOWS|1|0|0|0|0|0|0|0|0|1|0|0|0|0|Segoe UI"
        fontColor="#000000"
        lineColor="#5c5c5c"
        fillColor="#c8ffc8"
        type="1">
      <sourceConnections
          xsi:type="archimate:DiagramModelArchimateConnection"
          id="id-22429f96"
          font="1|Segoe UI|9.0|0|WINDOWS|1|0|0|0|0|0|0|0|0|1|0|0|0|0|Segoe UI"
          fontColor="#000000"
          lineColor="#000000"
          source="d5c17911"
          target="id-5607008f">
        <archimateRelationship
            xsi:type="archimate:RealizationRelationship"
            href="RealizationRelationship_a3d1a87a.xml#a3d1a87a"/>
      </sourceConnections>
      <bounds
          x="550"
          y="46"
          width="120"
          height="55"/>
      <archimateElement
          xsi:type="archimate:Node"
          href="Node_id-0b3081d8.xml#id-0b3081d8"/>
    </children>
    <children
        xsi:type="archimate:DiagramModelArchimateObject"
        id="id-4bfbffff"
        targetConnections="f28b544e"
        font="1|Segoe UI|9.0|0|WINDOWS|1|0|0|0|0|0|0|0|0|1|0|0|0|0|Segoe UI"
        fontColor="#000000"
        lineColor="#5c5c5c"
        fillColor="#c8ffc8"
        type="1">
      <sourceConnections
          xsi:type="archimate:DiagramModelArchimateConnection"
          id="f3cfdf7a-7054-49eb-add2-368f6e9529c5"
          font="1|Segoe UI|9.0|0|WINDOWS|1|0|0|0|0|0|0|0|0|1|0|0|0|0|Segoe UI"
          fontColor="#000000"
          lineColor="#000000"
          source="id-4bfbffff"
          target="id-2320e869-ecef-4683-b901-0bc65b358137">
        <archimateRelationship
            xsi:type="archimate:RealizationRelationship"
            href="RealizationRelationship_d204c5fd.xml#d204c5fd"/>
      </sourceConnections>
      <bounds
          x="300"
          y="46"
          width="201"
          height="55"/>
      <archimateElement
          xsi:type="archimate:Node"
          href="Node_id-2fe824f2.xml#id-2fe824f2"/>
    </children>
    <children
        xsi:type="archimate:DiagramModelArchimateObject"
        id="id-09eab30d"
        targetConnections="id-09de74d8 id-412cf18a"
        font="1|Segoe UI|9.0|0|WINDOWS|1|0|0|0|0|0|0|0|0|1|0|0|0|0|Segoe UI"
        fontColor="#000000"
        lineColor="#5c5c5c"
        fillColor="#c8ffc8">
      <bounds
          x="1150"
          y="185"
          width="251"
          height="55"/>
      <children
          xsi:type="archimate:DiagramModelReference"
          id="id-3f9698e5"
          font="1|Segoe UI|9.0|0|WINDOWS|1|0|0|0|0|0|0|0|0|1|0|0|0|0|Segoe UI"
          fontColor="#000000"
          lineColor="#5c5c5c"
          fillColor="#dcebeb">
        <bounds
            x="192"
            y="24"
            width="37"
            height="25"/>
        <referencedModel
            xsi:type="archimate:ArchimateDiagramModel"
            href="ArchimateDiagramModel_e7fc05db.xml#e7fc05db"/>
      </children>
      <archimateElement
          xsi:type="archimate:TechnologyService"
          href="TechnologyService_id-54561fe4.xml#id-54561fe4"/>
    </children>
  </children>
  <children
      xsi:type="archimate:DiagramModelNote"
      id="id-684b2376"
      font="1|Segoe UI|20.0|1|WINDOWS|1|0|0|0|0|700|0|0|0|1|0|0|0|0|Segoe UI"
      fontColor="#000000"
      lineColor="#5c5c5c"
      textAlignment="1"
      fillColor="#ffffff"
      content="TB_KK_SCH (2020): Technologická vrstva JPMIS">
    <bounds
        x="50"
        width="1351"
        height="51"/>
  </children>
  <children
      xsi:type="archimate:DiagramModelGroup"
      id="d01e674e"
      name="Legenda"
      font="1|Segoe UI|9.0|0|WINDOWS|1|0|0|0|0|0|0|0|0|1|0|0|0|0|Segoe UI"
      fontColor="#000000"
      lineColor="#5c5c5c"
      textAlignment="1"
      fillColor="#ffffff">
    <bounds
        x="50"
        y="700"
        width="302"
        height="249"/>
    <children
        xsi:type="archimate:DiagramModelNote"
        id="id-645effab"
        font="1|Segoe UI|9.0|0|WINDOWS|1|0|0|0|0|0|0|0|0|1|0|0|0|0|Segoe UI"
        fontColor="#000000"
        lineColor="#5c5c5c"
        textAlignment="1"
        fillColor="#ffffb5">
      <bounds
          x="8"
          y="24"
          width="41"
          height="37"/>
    </children>
    <children
        xsi:type="archimate:DiagramModelNote"
        id="baccf506"
        font="1|Segoe UI|9.0|0|WINDOWS|1|0|0|0|0|0|0|0|0|1|0|0|0|0|Segoe UI"
        fontColor="#000000"
        lineColor="#5c5c5c"
        textAlignment="1"
        fillColor="#86ff86">
      <bounds
          x="48"
          y="96"
          width="41"
          height="37"/>
    </children>
    <children
        xsi:type="archimate:DiagramModelNote"
        id="id-895b302a"
        font="1|Segoe UI|9.0|0|WINDOWS|1|0|0|0|0|0|0|0|0|1|0|0|0|0|Segoe UI"
        fontColor="#000000"
        lineColor="#5c5c5c"
        textAlignment="1"
        fillColor="#c9e7b7">
      <bounds
          x="8"
          y="96"
          width="41"
          height="37"/>
    </children>
    <children
        xsi:type="archimate:DiagramModelNote"
        id="id-62158591"
        font="1|Arial Narrow|8.0|0|WINDOWS|1|0|0|0|0|0|0|0|0|1|0|0|0|0|Arial Narrow"
        fontColor="#000000"
        lineColor="#5c5c5c"
        textAlignment="1"
        fillColor="#ffffff"
        content="Technologické komponenty  1) Technologie 2) Infrastruktura">
      <bounds
          x="132"
          y="96"
          width="157"
          height="37"/>
    </children>
    <children
        xsi:type="archimate:DiagramModelNote"
        id="ea7c83db"
        font="1|Arial Narrow|8.0|0|WINDOWS|1|0|0|0|0|0|0|0|0|1|0|0|0|0|Arial Narrow"
        fontColor="#000000"
        lineColor="#5c5c5c"
        textAlignment="1"
        fillColor="#ffffff"
        content="Nové komponenty (2020)">
      <bounds
          x="132"
          y="132"
          width="157"
          height="37"/>
    </children>
    <children
        xsi:type="archimate:DiagramModelNote"
        id="id-024d992f"
        font="1|Segoe UI|9.0|0|WINDOWS|1|0|0|0|0|0|0|0|0|1|0|0|0|0|Segoe UI"
        fontColor="#000000"
        lineColor="#5c5c5c"
        textAlignment="1"
        fillColor="#ffeaff">
      <bounds
          x="8"
          y="132"
          width="41"
          height="37"/>
    </children>
    <children
        xsi:type="archimate:DiagramModelNote"
        id="id-757c7601"
        font="1|Arial Narrow|8.0|0|WINDOWS|1|0|0|0|0|0|0|0|0|1|0|0|0|0|Arial Narrow"
        fontColor="#000000"
        lineColor="#5c5c5c"
        textAlignment="1"
        fillColor="#ffffff"
        content="Komponenty organizační vrstvy">
      <bounds
          x="132"
          y="24"
          width="157"
          height="37"/>
    </children>
    <children
        xsi:type="archimate:DiagramModelNote"
        id="id-3b19f52e"
        font="1|Arial Narrow|8.0|0|WINDOWS|1|0|0|0|0|0|0|0|0|1|0|0|0|0|Arial Narrow"
        fontColor="#000000"
        lineColor="#5c5c5c"
        textAlignment="1"
        fillColor="#ffffff"
        content="Aplikačn komponenty">
      <bounds
          x="132"
          y="60"
          width="157"
          height="37"/>
    </children>
    <children
        xsi:type="archimate:DiagramModelNote"
        id="d17ba89d"
        font="1|Segoe UI|9.0|0|WINDOWS|1|0|0|0|0|0|0|0|0|1|0|0|0|0|Segoe UI"
        fontColor="#000000"
        lineColor="#5c5c5c"
        textAlignment="1"
        fillColor="#b5ffff">
      <bounds
          x="8"
          y="60"
          width="41"
          height="37"/>
    </children>
  </children>
  <properties
      key="Organizace_Popisovana"
      value="KK"/>
</archimate:ArchimateDiagramModel>
