<archimate:ArchimateDiagramModel
    xmlns:xsi="http://www.w3.org/2001/XMLSchema-instance"
    xmlns:archimate="http://www.archimatetool.com/archimate"
    name="AS_KK_SCH: JPMS rozšiřující moduly detail - Hodnocení"
    id="id-d8566a036aaa4d538c1b44f94902b5c4"
    viewpoint="application_cooperation">
  <children
      xsi:type="archimate:DiagramModelNote"
      id="id-be691eaf08f846edb6aa88eb5f921663"
      font="1|Segoe UI|20.0|1|WINDOWS|1|0|0|0|0|700|0|0|0|1|0|0|0|0|Segoe UI"
      fontColor="#000000"
      lineColor="#5c5c5c"
      textAlignment="1"
      fillColor="#ffffff"
      content="AS_KK_SCH: JPMS Moduly detail - Hodnocení">
    <bounds
        x="-24"
        y="-168"
        width="792"
        height="51"/>
  </children>
  <children
      xsi:type="archimate:DiagramModelArchimateObject"
      id="id-910ad1a2a562404ea6b368950aa7417a"
      type="1">
    <sourceConnections
        xsi:type="archimate:DiagramModelArchimateConnection"
        id="id-59f6c32be4b04379bf83b104e7f0fa37"
        source="id-910ad1a2a562404ea6b368950aa7417a"
        target="id-03a20bc5a84e4811907d9c30381c1860">
      <archimateRelationship
          xsi:type="archimate:CompositionRelationship"
          href="CompositionRelationship_id-12905782b6724f0db709110909f8d9bf.xml#id-12905782b6724f0db709110909f8d9bf"/>
    </sourceConnections>
    <bounds
        x="-24"
        y="-96"
        width="792"
        height="60"/>
    <archimateElement
        xsi:type="archimate:ApplicationComponent"
        href="ApplicationComponent_id-837af71e41c6418087c250e1a2c25670.xml#id-837af71e41c6418087c250e1a2c25670"/>
  </children>
  <children
      xsi:type="archimate:DiagramModelGroup"
      id="id-ff393bdbde4d4bec980a411b78e44b20"
      name="Legenda"
      font="1|Segoe UI|9.0|0|WINDOWS|1|0|0|0|0|0|0|0|0|1|0|0|0|0|Segoe UI"
      fontColor="#000000"
      lineColor="#5c5c5c"
      textAlignment="1"
      fillColor="#ffffff">
    <bounds
        x="-12"
        y="228"
        width="302"
        height="249"/>
    <children
        xsi:type="archimate:DiagramModelNote"
        id="id-c5f910680d454055bfeb81a988ad6d3d"
        font="1|Segoe UI|9.0|0|WINDOWS|1|0|0|0|0|0|0|0|0|1|0|0|0|0|Segoe UI"
        fontColor="#000000"
        lineColor="#5c5c5c"
        textAlignment="1"
        fillColor="#ffffb5">
      <bounds
          x="8"
          y="24"
          width="41"
          height="37"/>
    </children>
    <children
        xsi:type="archimate:DiagramModelNote"
        id="id-2dd29945438647fbbc1167460032108a"
        font="1|Segoe UI|9.0|0|WINDOWS|1|0|0|0|0|0|0|0|0|1|0|0|0|0|Segoe UI"
        fontColor="#000000"
        lineColor="#5c5c5c"
        textAlignment="1"
        fillColor="#86ff86">
      <bounds
          x="48"
          y="96"
          width="41"
          height="37"/>
    </children>
    <children
        xsi:type="archimate:DiagramModelNote"
        id="id-546f05278757420c96e968e3f311795d"
        font="1|Segoe UI|9.0|0|WINDOWS|1|0|0|0|0|0|0|0|0|1|0|0|0|0|Segoe UI"
        fontColor="#000000"
        lineColor="#5c5c5c"
        textAlignment="1"
        fillColor="#c9e7b7">
      <bounds
          x="8"
          y="96"
          width="41"
          height="37"/>
    </children>
    <children
        xsi:type="archimate:DiagramModelNote"
        id="id-99ee4762ccf4473c90f6a49271780448"
        font="1|Arial Narrow|8.0|0|WINDOWS|1|0|0|0|0|0|0|0|0|1|0|0|0|0|Arial Narrow"
        fontColor="#000000"
        lineColor="#5c5c5c"
        textAlignment="1"
        fillColor="#ffffff"
        content="Technologické komponenty  1) Technologie 2) Infrastruktura">
      <bounds
          x="132"
          y="96"
          width="157"
          height="37"/>
    </children>
    <children
        xsi:type="archimate:DiagramModelNote"
        id="id-0d7b0f1978154bccb390b56fd517e1ff"
        font="1|Arial Narrow|8.0|0|WINDOWS|1|0|0|0|0|0|0|0|0|1|0|0|0|0|Arial Narrow"
        fontColor="#000000"
        lineColor="#5c5c5c"
        textAlignment="1"
        fillColor="#ffffff"
        content="Nové komponenty">
      <bounds
          x="132"
          y="132"
          width="157"
          height="37"/>
    </children>
    <children
        xsi:type="archimate:DiagramModelNote"
        id="id-2e9cb442d33043b58f1f2668695b0ab6"
        font="1|Segoe UI|9.0|0|WINDOWS|1|0|0|0|0|0|0|0|0|1|0|0|0|0|Segoe UI"
        fontColor="#000000"
        lineColor="#5c5c5c"
        textAlignment="1"
        fillColor="#ffeaff">
      <bounds
          x="8"
          y="132"
          width="41"
          height="37"/>
    </children>
    <children
        xsi:type="archimate:DiagramModelNote"
        id="id-f37fd3227c6f422785fa629a7cb689bc"
        font="1|Arial Narrow|8.0|0|WINDOWS|1|0|0|0|0|0|0|0|0|1|0|0|0|0|Arial Narrow"
        fontColor="#000000"
        lineColor="#5c5c5c"
        textAlignment="1"
        fillColor="#ffffff"
        content="Komponenty organizační vrstvy">
      <bounds
          x="132"
          y="24"
          width="157"
          height="37"/>
    </children>
    <children
        xsi:type="archimate:DiagramModelNote"
        id="id-400c2750c17d4fec9b6f4b93ef87a9d2"
        font="1|Arial Narrow|8.0|0|WINDOWS|1|0|0|0|0|0|0|0|0|1|0|0|0|0|Arial Narrow"
        fontColor="#000000"
        lineColor="#5c5c5c"
        textAlignment="1"
        fillColor="#ffffff"
        content="Aplikační komponenty&#xD;&#xA;1. místní 2. sdílené 3. externí">
      <bounds
          x="132"
          y="60"
          width="157"
          height="37"/>
    </children>
    <children
        xsi:type="archimate:DiagramModelNote"
        id="id-579850ca6aae4211a591d28a409248c5"
        font="1|Segoe UI|9.0|0|WINDOWS|1|0|0|0|0|0|0|0|0|1|0|0|0|0|Segoe UI"
        fontColor="#000000"
        lineColor="#5c5c5c"
        textAlignment="1"
        fillColor="#b5ffff">
      <bounds
          x="8"
          y="60"
          width="41"
          height="37"/>
    </children>
    <children
        xsi:type="archimate:DiagramModelNote"
        id="id-92f2c4e29bed4070bf73e5dd4ca00a54"
        font="1|Segoe UI|9.0|0|WINDOWS|1|0|0|0|0|0|0|0|0|1|0|0|0|0|Segoe UI"
        fontColor="#000000"
        lineColor="#5c5c5c"
        textAlignment="1"
        fillColor="#53a9ff">
      <bounds
          x="88"
          y="60"
          width="41"
          height="37"/>
    </children>
    <children
        xsi:type="archimate:DiagramModelNote"
        id="id-92b25bb95ac4438994479dbe75ae558b"
        font="1|Segoe UI|9.0|0|WINDOWS|1|0|0|0|0|0|0|0|0|1|0|0|0|0|Segoe UI"
        fontColor="#000000"
        lineColor="#5c5c5c"
        textAlignment="1"
        fillColor="#00ffff">
      <bounds
          x="48"
          y="60"
          width="41"
          height="37"/>
    </children>
  </children>
  <children
      xsi:type="archimate:DiagramModelArchimateObject"
      id="id-03a20bc5a84e4811907d9c30381c1860"
      targetConnections="id-59f6c32be4b04379bf83b104e7f0fa37"
      type="1">
    <sourceConnections
        xsi:type="archimate:DiagramModelArchimateConnection"
        id="id-beb94c56f2a24dac98bb5f31d43d2219"
        source="id-03a20bc5a84e4811907d9c30381c1860"
        target="id-e1ad7df8251c435ab4d697529269aa71">
      <archimateRelationship
          xsi:type="archimate:AssignmentRelationship"
          href="AssignmentRelationship_id-64771c7604084e4ea0eb166d6c0ea130.xml#id-64771c7604084e4ea0eb166d6c0ea130"/>
    </sourceConnections>
    <sourceConnections
        xsi:type="archimate:DiagramModelArchimateConnection"
        id="id-79075a627b604f5caf22ca1b60e8462d"
        source="id-03a20bc5a84e4811907d9c30381c1860"
        target="id-c1d95b3c39f64efd81b426debb3246a0">
      <archimateRelationship
          xsi:type="archimate:AssignmentRelationship"
          href="AssignmentRelationship_id-e9ab7363da5445e0b072ed7440426b53.xml#id-e9ab7363da5445e0b072ed7440426b53"/>
    </sourceConnections>
    <bounds
        x="-24"
        y="36"
        width="434"
        height="120"/>
    <children
        xsi:type="archimate:DiagramModelArchimateObject"
        id="id-e1ad7df8251c435ab4d697529269aa71"
        targetConnections="id-beb94c56f2a24dac98bb5f31d43d2219">
      <bounds
          x="60"
          y="36"
          width="120"
          height="55"/>
      <archimateElement
          xsi:type="archimate:ApplicationFunction"
          href="ApplicationFunction_id-43fcad33c6bc4577a9c3edad3666404f.xml#id-43fcad33c6bc4577a9c3edad3666404f"/>
    </children>
    <children
        xsi:type="archimate:DiagramModelArchimateObject"
        id="id-c1d95b3c39f64efd81b426debb3246a0"
        targetConnections="id-79075a627b604f5caf22ca1b60e8462d">
      <sourceConnections
          xsi:type="archimate:DiagramModelArchimateConnection"
          id="id-0e2d129ed0a84cb98b89a83fd69a65d1"
          source="id-c1d95b3c39f64efd81b426debb3246a0"
          target="id-f761621111f141e2a94b0a3573e89835">
        <archimateRelationship
            xsi:type="archimate:AccessRelationship"
            href="AccessRelationship_id-8ea5600ebd66476e9499f1a9886e94ba.xml#id-8ea5600ebd66476e9499f1a9886e94ba"/>
      </sourceConnections>
      <bounds
          x="264"
          y="36"
          width="120"
          height="55"/>
      <archimateElement
          xsi:type="archimate:ApplicationFunction"
          href="ApplicationFunction_id-b482d82351fc4ee58f4be47086375d5e.xml#id-b482d82351fc4ee58f4be47086375d5e"/>
    </children>
    <archimateElement
        xsi:type="archimate:ApplicationComponent"
        href="ApplicationComponent_id-2dbdc9c61c7345da86d6e340d268d0b5.xml#id-2dbdc9c61c7345da86d6e340d268d0b5"/>
  </children>
  <children
      xsi:type="archimate:DiagramModelArchimateObject"
      id="id-f761621111f141e2a94b0a3573e89835"
      targetConnections="id-0e2d129ed0a84cb98b89a83fd69a65d1"
      type="1">
    <bounds
        x="648"
        y="72"
        width="120"
        height="55"/>
    <archimateElement
        xsi:type="archimate:DataObject"
        href="DataObject_id-c2f40b0b3a1c4389b2cdf4fa7bcd0883.xml#id-c2f40b0b3a1c4389b2cdf4fa7bcd0883"/>
  </children>
</archimate:ArchimateDiagramModel>
